econnlp/__init__.py
econnlp/embedding/__init__.py
econnlp/embedding/docs.py
econnlp-0.0.7.dist-info/LICENSE
econnlp-0.0.7.dist-info/METADATA
econnlp-0.0.7.dist-info/WHEEL
econnlp-0.0.7.dist-info/top_level.txt
econnlp-0.0.7.dist-info/RECORD
