Metadata-Version: 2.1
Name: econnlp
Version: 0.0.7
Summary: An Econ Approach to NLP
Home-page: https://github.com/muhlbach/econnlp
Author: Nicolaj Søndergaard Mühlbach
Author-email: n.muhlbach@gmail.com
License: MIT License
Keywords: natural language processing,deep learning,machine learning
Platform: UNKNOWN
Classifier: Programming Language :: Python :: 3
Classifier: License :: OSI Approved :: MIT License
Classifier: Operating System :: OS Independent
Requires-Python: >=3.6
License-File: LICENSE
Requires-Dist: bodyguard (>=0.0.23)
